xwind-1.4.2.dist-info/METADATA
xwind-1.4.2.dist-info/WHEEL
xwind/data_functions/direction.py
xwind/data_functions/linregress.py
xwind/data_functions/__init__.py
xwind/distribution/joint_probability_distribution.py
xwind/distribution/wbl_distribution.py
xwind/distribution/WeibullDistributionCreator.py
xwind/distribution/__init__.py
xwind/general_functions/get_content_fromZipfile.py
xwind/general_functions/get_encoding.py
xwind/general_functions/get_files_byEndString.py
xwind/general_functions/interpolate.py
xwind/general_functions/MCP.py
xwind/general_functions/wind_direction_average.py
xwind/general_functions/__init__.py
xwind/gis/deal_longlat.py
xwind/gis/epsg_finder.py
xwind/gis/gcj02coordinates.py
xwind/gis/kml/3D-turbine-91mHH.dae
xwind/gis/kml/add_3d_model.py
xwind/gis/kml/__init__.py
xwind/gis/objects/geo_point.py
xwind/gis/objects/__init__.py
xwind/gis/proj.py
xwind/gis/__init__.py
xwind/py.typed
xwind/rs_funcs.pyi
xwind/standards/common.py
xwind/standards/IEC61400_1_1999.py
xwind/standards/IEC61400_1_2005.py
xwind/standards/IEC61400_1_2010.py
xwind/standards/IEC61400_1_2019.py
xwind/standards/__init__.py
xwind/turbine/perfermance_table.py
xwind/turbine/properties/power_curve.py
xwind/turbine/properties/__init__.py
xwind/turbine/__init__.py
xwind/utils/appdirs.py
xwind/utils/calculator/calc_prod.ipynb
xwind/utils/calculator/production.py
xwind/utils/calculator/production_calculator.py
xwind/utils/calculator/__init__.py
xwind/utils/echarts/echarts.js
xwind/utils/echarts/echarts_ssr.mjs
xwind/utils/echarts/echarts_ssr.py
xwind/utils/file_io/get_ext_files.py
xwind/utils/file_io/merge_csv.py
xwind/utils/file_io/merge_txt.py
xwind/utils/file_io/parse_xml.py
xwind/utils/file_io/__init__.py
xwind/utils/rar/main.py
xwind/utils/rar/__init__.py
xwind/utils/skip_to_line.py
xwind/utils/tab_converter.py
xwind/utils/transform_WT_4_to_5/main.py
xwind/utils/transform_WT_4_to_5/transform_freq_4_to_5.py
xwind/utils/transform_WT_4_to_5/transform_result_4_to_5.py
xwind/utils/transform_WT_4_to_5/transform_turb_4_to_5.py
xwind-1.4.2.dist-info/RECORD
