Metadata-Version: 2.3
Name: xwind
Version: 1.4.2
Classifier: Development Status :: 4 - Beta
Classifier: Environment :: Console
Classifier: Intended Audience :: Science/Research
Classifier: Operating System :: OS Independent
Classifier: Programming Language :: Python
Classifier: Programming Language :: Python :: 3
Classifier: Programming Language :: Python :: 3 :: Only
Classifier: Programming Language :: Python :: 3.9
Classifier: Programming Language :: Python :: 3.10
Classifier: Programming Language :: Python :: 3.11
Classifier: Programming Language :: Python :: 3.12
Classifier: Topic :: Scientific/Engineering :: Atmospheric Science
Requires-Dist: pandas[computation,excel] >=2.0
Requires-Dist: numpy
Requires-Dist: scipy
Requires-Dist: simplekml
Requires-Dist: pyproj
Requires-Dist: deprecated
Requires-Dist: chardet
Requires-Dist: bottleneck ; extra == 'performance'
Requires-Dist: numexpr ; extra == 'performance'
Requires-Dist: pytest ; extra == 'test'
Requires-Dist: ipykernel ; extra == 'test'
Requires-Dist: pyecharts ; extra == 'test'
Provides-Extra: performance
Provides-Extra: test
Summary: 风资源工具基础库
Author-email: HuQin <hu578344563@163.com>
Maintainer: xwind contributors
License: BSD-3-Clause
Requires-Python: >=3.9
